brui_core/__init__.py
brui_core/singleton_meta.py
brui_core/ui_integrator.py
brui_core/browser/__init__.py
brui_core/browser/browser_launcher.py
brui_core/browser/browser_manager.py
brui_core/clipboard/__init__.py
brui_core/clipboard/clipboard_manager.py
brui_core-1.2.1.dist-info/METADATA
brui_core-1.2.1.dist-info/WHEEL
brui_core-1.2.1.dist-info/top_level.txt
brui_core-1.2.1.dist-info/RECORD
