Metadata-Version: 2.4
Name: brui_core
Version: 1.2.1
Summary: Core browser UI automation framework
Author-email: Ryan Zheng <ryan.zheng.work@gmail.com>
License: MIT
Project-URL: Homepage, https://github.com/AutoByteus/brui_core.git
Project-URL: Source, https://github.com/AutoByteus/brui_core.git
Classifier: Development Status :: 4 - Beta
Classifier: Intended Audience :: Developers
Classifier: License :: OSI Approved :: MIT License
Classifier: Programming Language :: Python :: 3
Classifier: Programming Language :: Python :: 3.8
Classifier: Programming Language :: Python :: 3.9
Classifier: Programming Language :: Python :: 3.10
Classifier: Topic :: Software Development :: Libraries :: Python Modules
Classifier: Topic :: Software Development :: Testing
Requires-Python: >=3.11
Requires-Dist: playwright==1.55.0
Requires-Dist: pyperclip
Requires-Dist: Pillow
Provides-Extra: test
Requires-Dist: pytest-playwright==0.4.4; extra == "test"
Requires-Dist: playwright==1.55.0; extra == "test"
Requires-Dist: pytest-asyncio; extra == "test"
